wic/Config.py
wic/__init__.py
wic/cli.py
wic/files.py
wic/options.py
wic/workspace.py
wic-0.2.dist-info/METADATA
wic-0.2.dist-info/WHEEL
wic-0.2.dist-info/entry_points.txt
wic-0.2.dist-info/top_level.txt
wic-0.2.dist-info/RECORD
