Metadata-Version: 2.1
Name: wic
Version: 0.2
Summary: winIDEA command line interface
Home-page: https://github.com/hacki11/wic
Author: Juergen Schmid
Author-email: jur.schmid@gmail.com
License: apache-2.0
Keywords: isystem,winidea,cli
Platform: UNKNOWN
Classifier: Intended Audience :: Developers
Classifier: Topic :: Software Development :: Build Tools
Classifier: License :: OSI Approved :: Apache Software License
Classifier: Programming Language :: Python :: 3
Classifier: Programming Language :: Python :: 3.8
Requires-Dist: click
